{
  "as_of_utc": "2025-10-28T22:24:55.297681+00:00",
  "timeframe": "1Day",
  "indicators_window": 150,
  "symbols": {
    "QBTS": {
      "symbol": "QBTS",
      "price": 32,
      "ts": "2025-10-28T04:00:00Z",
      "sector": "",
      "signals": {
        "TS": 0.0,
        "NS": 0.0,
        "wT": 0.6,
        "wN": 0.4,
        "CDS": 0.0,
        "components": {
          "rsi_pos": 0.0,
          "macd_hist_slope": 0.0,
          "ema20_slope": 0.0
        },
        "ts_debug": {
          "rsi": "missing_rsi",
          "macd": "macd_hist",
          "ema": "missing_ema_and_price"
        },
        "ns_debug": {
          "source": "default_neutral",
          "articles_used": 0
        },
        "sector_debug": {
          "sector_avg": {
            "Unknown": 0.0
          },
          "notes": "nudge applied when sign disagrees"
        }
      },
      "decision": "Hold"
    },
    "VTI": {
      "symbol": "VTI",
      "price": 337.95,
      "ts": "2025-10-28T04:00:00Z",
      "sector": "",
      "signals": {
        "TS": 0.0,
        "NS": 0.0,
        "wT": 0.6,
        "wN": 0.4,
        "CDS": 0.0,
        "components": {
          "rsi_pos": 0.0,
          "macd_hist_slope": 0.0,
          "ema20_slope": 0.0
        },
        "ts_debug": {
          "rsi": "missing_rsi",
          "macd": "macd_hist",
          "ema": "missing_ema_and_price"
        },
        "ns_debug": {
          "source": "default_neutral",
          "articles_used": 0
        },
        "sector_debug": {
          "sector_avg": {
            "Unknown": 0.0
          },
          "notes": "nudge applied when sign disagrees"
        }
      },
      "decision": "Hold"
    },
    "QUBT": {
      "symbol": "QUBT",
      "price": 14.91,
      "ts": "2025-10-28T04:00:00Z",
      "sector": "",
      "signals": {
        "TS": 0.0,
        "NS": 0.0,
        "wT": 0.6,
        "wN": 0.4,
        "CDS": 0.0,
        "components": {
          "rsi_pos": 0.0,
          "macd_hist_slope": 0.0,
          "ema20_slope": 0.0
        },
        "ts_debug": {
          "rsi": "missing_rsi",
          "macd": "macd_hist",
          "ema": "missing_ema_and_price"
        },
        "ns_debug": {
          "source": "default_neutral",
          "articles_used": 0
        },
        "sector_debug": {
          "sector_avg": {
            "Unknown": 0.0
          },
          "notes": "nudge applied when sign disagrees"
        }
      },
      "decision": "Hold"
    },
    "RGTI": {
      "symbol": "RGTI",
      "price": 37.07,
      "ts": "2025-10-28T04:00:00Z",
      "sector": "",
      "signals": {
        "TS": 0.0,
        "NS": 0.0,
        "wT": 0.6,
        "wN": 0.4,
        "CDS": 0.0,
        "components": {
          "rsi_pos": 0.0,
          "macd_hist_slope": 0.0,
          "ema20_slope": 0.0
        },
        "ts_debug": {
          "rsi": "missing_rsi",
          "macd": "macd_hist",
          "ema": "missing_ema_and_price"
        },
        "ns_debug": {
          "source": "default_neutral",
          "articles_used": 0
        },
        "sector_debug": {
          "sector_avg": {
            "Unknown": 0.0
          },
          "notes": "nudge applied when sign disagrees"
        }
      },
      "decision": "Hold"
    },
    "TTWO": {
      "symbol": "TTWO",
      "price": 251.57,
      "ts": "2025-10-28T04:00:00Z",
      "sector": "",
      "signals": {
        "TS": 0.0,
        "NS": 0.0,
        "wT": 0.6,
        "wN": 0.4,
        "CDS": 0.0,
        "components": {
          "rsi_pos": 0.0,
          "macd_hist_slope": 0.0,
          "ema20_slope": 0.0
        },
        "ts_debug": {
          "rsi": "missing_rsi",
          "macd": "macd_hist",
          "ema": "missing_ema_and_price"
        },
        "ns_debug": {
          "source": "default_neutral",
          "articles_used": 0
        },
        "sector_debug": {
          "sector_avg": {
            "Unknown": 0.0
          },
          "notes": "nudge applied when sign disagrees"
        }
      },
      "decision": "Hold"
    },
    "ASTS": {
      "symbol": "ASTS",
      "price": 77.77,
      "ts": "2025-10-28T04:00:00Z",
      "sector": "",
      "signals": {
        "TS": 0.0,
        "NS": 0.0,
        "wT": 0.6,
        "wN": 0.4,
        "CDS": 0.0,
        "components": {
          "rsi_pos": 0.0,
          "macd_hist_slope": 0.0,
          "ema20_slope": 0.0
        },
        "ts_debug": {
          "rsi": "missing_rsi",
          "macd": "macd_hist",
          "ema": "missing_ema_and_price"
        },
        "ns_debug": {
          "source": "default_neutral",
          "articles_used": 0
        },
        "sector_debug": {
          "sector_avg": {
            "Unknown": 0.0
          },
          "notes": "nudge applied when sign disagrees"
        }
      },
      "decision": "Hold"
    },
    "RKLB": {
      "symbol": "RKLB",
      "price": 63.75,
      "ts": "2025-10-28T04:00:00Z",
      "sector": "",
      "signals": {
        "TS": 0.0,
        "NS": 0.0,
        "wT": 0.6,
        "wN": 0.4,
        "CDS": 0.0,
        "components": {
          "rsi_pos": 0.0,
          "macd_hist_slope": 0.0,
          "ema20_slope": 0.0
        },
        "ts_debug": {
          "rsi": "missing_rsi",
          "macd": "macd_hist",
          "ema": "missing_ema_and_price"
        },
        "ns_debug": {
          "source": "default_neutral",
          "articles_used": 0
        },
        "sector_debug": {
          "sector_avg": {
            "Unknown": 0.0
          },
          "notes": "nudge applied when sign disagrees"
        }
      },
      "decision": "Hold"
    },
    "ARCC": {
      "symbol": "ARCC",
      "price": 20.57,
      "ts": "2025-10-28T04:00:00Z",
      "sector": "",
      "signals": {
        "TS": 0.0,
        "NS": 0.0,
        "wT": 0.6,
        "wN": 0.4,
        "CDS": 0.0,
        "components": {
          "rsi_pos": 0.0,
          "macd_hist_slope": 0.0,
          "ema20_slope": 0.0
        },
        "ts_debug": {
          "rsi": "missing_rsi",
          "macd": "macd_hist",
          "ema": "missing_ema_and_price"
        },
        "ns_debug": {
          "source": "default_neutral",
          "articles_used": 0
        },
        "sector_debug": {
          "sector_avg": {
            "Unknown": 0.0
          },
          "notes": "nudge applied when sign disagrees"
        }
      },
      "decision": "Hold"
    },
    "NVDA": {
      "symbol": "NVDA",
      "price": 201.03,
      "ts": "2025-10-28T04:00:00Z",
      "sector": "",
      "signals": {
        "TS": 0.0,
        "NS": 0.0,
        "wT": 0.6,
        "wN": 0.4,
        "CDS": 0.0,
        "components": {
          "rsi_pos": 0.0,
          "macd_hist_slope": 0.0,
          "ema20_slope": 0.0
        },
        "ts_debug": {
          "rsi": "missing_rsi",
          "macd": "macd_hist",
          "ema": "missing_ema_and_price"
        },
        "ns_debug": {
          "source": "default_neutral",
          "articles_used": 0
        },
        "sector_debug": {
          "sector_avg": {
            "Unknown": 0.0
          },
          "notes": "nudge applied when sign disagrees"
        }
      },
      "decision": "Hold"
    },
    "VOO": {
      "symbol": "VOO",
      "price": 631.69,
      "ts": "2025-10-28T04:00:00Z",
      "sector": "",
      "signals": {
        "TS": 0.0,
        "NS": 0.0,
        "wT": 0.6,
        "wN": 0.4,
        "CDS": 0.0,
        "components": {
          "rsi_pos": 0.0,
          "macd_hist_slope": 0.0,
          "ema20_slope": 0.0
        },
        "ts_debug": {
          "rsi": "missing_rsi",
          "macd": "macd_hist",
          "ema": "missing_ema_and_price"
        },
        "ns_debug": {
          "source": "default_neutral",
          "articles_used": 0
        },
        "sector_debug": {
          "sector_avg": {
            "Unknown": 0.0
          },
          "notes": "nudge applied when sign disagrees"
        }
      },
      "decision": "Hold"
    },
    "AMZN": {
      "symbol": "AMZN",
      "price": 229.25,
      "ts": "2025-10-28T04:00:00Z",
      "sector": "",
      "signals": {
        "TS": 0.0,
        "NS": 0.0,
        "wT": 0.6,
        "wN": 0.4,
        "CDS": 0.0,
        "components": {
          "rsi_pos": 0.0,
          "macd_hist_slope": 0.0,
          "ema20_slope": 0.0
        },
        "ts_debug": {
          "rsi": "missing_rsi",
          "macd": "macd_hist",
          "ema": "missing_ema_and_price"
        },
        "ns_debug": {
          "source": "default_neutral",
          "articles_used": 0
        },
        "sector_debug": {
          "sector_avg": {
            "Unknown": 0.0
          },
          "notes": "nudge applied when sign disagrees"
        }
      },
      "decision": "Hold"
    },
    "SNOW": {
      "symbol": "SNOW",
      "price": 267.05,
      "ts": "2025-10-28T04:00:00Z",
      "sector": "",
      "signals": {
        "TS": 0.0,
        "NS": 0.0,
        "wT": 0.6,
        "wN": 0.4,
        "CDS": 0.0,
        "components": {
          "rsi_pos": 0.0,
          "macd_hist_slope": 0.0,
          "ema20_slope": 0.0
        },
        "ts_debug": {
          "rsi": "missing_rsi",
          "macd": "macd_hist",
          "ema": "missing_ema_and_price"
        },
        "ns_debug": {
          "source": "default_neutral",
          "articles_used": 0
        },
        "sector_debug": {
          "sector_avg": {
            "Unknown": 0.0
          },
          "notes": "nudge applied when sign disagrees"
        }
      },
      "decision": "Hold"
    },
    "PLTR": {
      "symbol": "PLTR",
      "price": 189.6,
      "ts": "2025-10-28T04:00:00Z",
      "sector": "",
      "signals": {
        "TS": 0.0,
        "NS": 0.0,
        "wT": 0.6,
        "wN": 0.4,
        "CDS": 0.0,
        "components": {
          "rsi_pos": 0.0,
          "macd_hist_slope": 0.0,
          "ema20_slope": 0.0
        },
        "ts_debug": {
          "rsi": "missing_rsi",
          "macd": "macd_hist",
          "ema": "missing_ema_and_price"
        },
        "ns_debug": {
          "source": "default_neutral",
          "articles_used": 0
        },
        "sector_debug": {
          "sector_avg": {
            "Unknown": 0.0
          },
          "notes": "nudge applied when sign disagrees"
        }
      },
      "decision": "Hold"
    },
    "AMD": {
      "symbol": "AMD",
      "price": 258.01,
      "ts": "2025-10-28T04:00:00Z",
      "sector": "",
      "signals": {
        "TS": 0.0,
        "NS": 0.0,
        "wT": 0.6,
        "wN": 0.4,
        "CDS": 0.0,
        "components": {
          "rsi_pos": 0.0,
          "macd_hist_slope": 0.0,
          "ema20_slope": 0.0
        },
        "ts_debug": {
          "rsi": "missing_rsi",
          "macd": "macd_hist",
          "ema": "missing_ema_and_price"
        },
        "ns_debug": {
          "source": "default_neutral",
          "articles_used": 0
        },
        "sector_debug": {
          "sector_avg": {
            "Unknown": 0.0
          },
          "notes": "nudge applied when sign disagrees"
        }
      },
      "decision": "Hold"
    },
    "DE": {
      "symbol": "DE",
      "price": 468.19,
      "ts": "2025-10-28T04:00:00Z",
      "sector": "",
      "signals": {
        "TS": 0.0,
        "NS": 0.0,
        "wT": 0.6,
        "wN": 0.4,
        "CDS": 0.0,
        "components": {
          "rsi_pos": 0.0,
          "macd_hist_slope": 0.0,
          "ema20_slope": 0.0
        },
        "ts_debug": {
          "rsi": "missing_rsi",
          "macd": "macd_hist",
          "ema": "missing_ema_and_price"
        },
        "ns_debug": {
          "source": "default_neutral",
          "articles_used": 0
        },
        "sector_debug": {
          "sector_avg": {
            "Unknown": 0.0
          },
          "notes": "nudge applied when sign disagrees"
        }
      },
      "decision": "Hold"
    }
  }
}