{
  "as_of_utc": "2025-11-06T04:21:01.973181+00:00",
  "criteria": {
    "TS_WATCH": 0.5,
    "NS_WATCH": 0.5,
    "TOP": 20
  },
  "items": [
    {
      "symbol": "AAPL",
      "price": 270.11,
      "TS": 0.590971,
      "NS": 0.363634,
      "CDS": 0.500036
    },
    {
      "symbol": "FSLR",
      "price": 277.31,
      "TS": 0.641101,
      "NS": 0.27028,
      "CDS": 0.492773
    },
    {
      "symbol": "AMZN",
      "price": 250.245,
      "TS": 0.612164,
      "NS": 0.261789,
      "CDS": 0.472014
    },
    {
      "symbol": "GOOGL",
      "price": 284.34,
      "TS": 0.630506,
      "NS": 0.120099,
      "CDS": 0.426343
    },
    {
      "symbol": "DE",
      "price": 473.85,
      "TS": 0.524608,
      "NS": 0.256281,
      "CDS": 0.417277
    },
    {
      "symbol": "U",
      "price": 42.37,
      "TS": 0.578357,
      "NS": 0.15452,
      "CDS": 0.408823
    }
  ]
}